soku_configuration/__init__.py
soku_object/__init__.py
soku_service/__init__.py
soku-3.0.0.dist-info/LICENSE
soku-3.0.0.dist-info/METADATA
soku-3.0.0.dist-info/WHEEL
soku-3.0.0.dist-info/top_level.txt
soku-3.0.0.dist-info/RECORD
